fishtext/__init__.py
fishtext/api.py
fishtext/errors.py
fishtext/types.py
fish_text_ru-2.0.2.dist-info/LICENSE
fish_text_ru-2.0.2.dist-info/WHEEL
fish_text_ru-2.0.2.dist-info/METADATA
fish_text_ru-2.0.2.dist-info/RECORD
