Metadata-Version: 2.1
Name: fish-text-ru
Version: 2.0.2
Summary: Simple fish-text.ru python wrapper
Home-page: https://github.com/kiriharu/fish_text_ru
License: MIT
Keywords: fish text,autotext
Author: kiriharu
Author-email: kiriharu@yandex.ru
Requires-Python: >=3.7,<4.0
Classifier: Development Status :: 5 - Production/Stable
Classifier: Environment :: Console
Classifier: Intended Audience :: Developers
Classifier: License :: OSI Approved :: MIT License
Classifier: Natural Language :: Russian
Classifier: Programming Language :: Python :: 3
Classifier: Programming Language :: Python :: 3.7
Classifier: Programming Language :: Python :: 3.8
Classifier: Programming Language :: Python :: 3.9
Classifier: Topic :: Utilities
Classifier: Typing :: Typed
Requires-Dist: requests (>=2.25.1,<3.0.0)
Project-URL: Repository, https://github.com/kiriharu/fish_text_ru
